stramp/__init__.py
stramp/__main__.py
stramp/cli.py
stramp/configfile.py
stramp/docstruct.py
stramp/globalstate.py
stramp/hashing.py
stramp/paths.py
stramp/parsers/markdown_parser.py
stramp/parsers/org_parser.py
stramp-0.3.2.dist-info/LICENSE
stramp-0.3.2.dist-info/METADATA
stramp-0.3.2.dist-info/WHEEL
stramp-0.3.2.dist-info/entry_points.txt
stramp-0.3.2.dist-info/top_level.txt
stramp-0.3.2.dist-info/RECORD
