Metadata-Version: 2.1
Name: stramp
Version: 0.3.2
Summary: Blockchain-backed timestamp proof for structured document sections
Home-page: https://github.com/wonkyweirdy/stramp
Author: Ray Burr
Author-email: ryb@nightmare.com
License: mit
Keywords: blockchain timestamp opentimestamps
Platform: any
Classifier: Development Status :: 3 - Alpha
Classifier: Environment :: Console
Classifier: Intended Audience :: Developers
Classifier: Intended Audience :: End Users/Desktop
Classifier: Intended Audience :: System Administrators
Classifier: License :: OSI Approved :: MIT License
Classifier: Operating System :: OS Independent
Classifier: Programming Language :: Python
Classifier: Programming Language :: Python :: 3
Classifier: Programming Language :: Python :: 3 :: Only
Classifier: Programming Language :: Python :: 3.6
Classifier: Programming Language :: Python :: 3.7
Classifier: Programming Language :: Python :: 3.8
Classifier: Programming Language :: Python :: Implementation :: CPython
Classifier: Topic :: Utilities
Classifier: Topic :: Text Processing
Classifier: Topic :: Security :: Cryptography
Requires-Python: >=3.6
Requires-Dist: click (>=6.7)
Requires-Dist: anytree (>=2.7.2)
Requires-Dist: dataclasses (>=0.6) ; python_version < "3.7"
Requires-Dist: importlib-metadata (>=1.0) ; python_version < "3.8"
Provides-Extra: commonmark
Requires-Dist: marko ; extra == 'commonmark'
Provides-Extra: testing
Requires-Dist: pytest ; extra == 'testing'
Requires-Dist: pytest-cov ; extra == 'testing'
Requires-Dist: click ; extra == 'testing'
